dash_flask_keycloak/__init__.py
dash_flask_keycloak/core.py
dash_flask_keycloak/examples/__init__.py
dash_flask_keycloak/examples/dash_example.py
dash_flask_keycloak/examples/flask_example.py
dash_flask_keycloak-1.3.1.dist-info/METADATA
dash_flask_keycloak-1.3.1.dist-info/WHEEL
dash_flask_keycloak-1.3.1.dist-info/top_level.txt
dash_flask_keycloak-1.3.1.dist-info/RECORD
