Metadata-Version: 2.1
Name: dash-flask-keycloak
Version: 1.3.1
Summary: Extension providing Keycloak integration via the python-keycloak package to the Dash/Flask app
Home-page: https://github.com/Ilnur786/dash-flask-keycloak
Author: Ilnur Faizrakhmanov, Emil Haldrup Eriksen
Author-email: ilnurfrwork@gmail.com
License: MIT
Keywords: python,dash,flask,keycloak,pyjwt
Classifier: Programming Language :: Python :: 3
Requires-Python: >=3.8
Requires-Dist: flask >=3.0.0
Requires-Dist: PyJWT[crypto] >=2.0.0
Requires-Dist: python-keycloak >=3.0.0
